[
  {
    "title": "Basic Course",
    "image": "1.png",
    "content": "근골격 해부학, 기능 해부학, 스포츠 생리학, 신경계 해부학, 스포츠 영양학",
    "time": "180시간 12주 교육",
    "tags": ["해부학", "생리학"],
    "star": 5,
    "instructor": "강사명",
    "subtitle": "🔥 데이터베이스 설계 기초편에 이은 두 번째 강의입니다.",
    "keywords": ["데이터베이스 모델링 실전", "데이터베이스 설계"],
    "description": "실전 프로젝트를 대상으로 처음부터 끝까지 만들어보는 실전 위주의 수업이며, 강의 내용을 모두 이해하고 나면 자유자재로 데이터베이스 설계를 하실 수 있는 능력을 갖출 수 있습니다.",
    "banner": "그 누구도 알려주지 않았던 SQL, 잘 작성하고, 해석하고, 검증하는 비법 레시피!",
    "curriculum": [
      "사용자(회사), 시도, 시군구 테이블 만들기",
      "시도 시군구 뷰 만들기",
      "시도 시군구 저장프로시저 만들기",
      "Company 뷰, 저장함수 만들기",
      "테스트화면 개발, Model 클래스 개발",
      "사용자(직원) 만들기",
      "User 완성하기",
      "1:1관계를 가지고 사용자 속성 확장",
      "bit (boolean) 타입의 함정",
      "회사, 사용자 조회 및 삭제 구현",
      "삭제 트랜잭션 구현하기"
    ]
  },
  {
    "title": "Intermediate Course",
    "image": "2.png",
    "content": "심화된 과정으로 해부학, 체형 분석, 골프, 필라테스",
    "time": "180시간 12주 교육",
    "tags": ["해부학", "생리학"],
    "star": 5,
    "instructor": "강사명",
    "subtitle": "🔥 데이터베이스 설계 기초편에 이은 두 번째 강의입니다.",
    "keywords": ["데이터베이스 모델링 실전", "데이터베이스 설계"],
    "description": "실전 프로젝트를 대상으로 처음부터 끝까지 만들어보는 실전 위주의 수업이며, 강의 내용을 모두 이해하고 나면 자유자재로 데이터베이스 설계를 하실 수 있는 능력을 갖출 수 있습니다.",
    "banner": "그 누구도 알려주지 않았던 SQL, 잘 작성하고, 해석하고, 검증하는 비법 레시피!",
    "curriculum": [
      "사용자(회사), 시도, 시군구 테이블 만들기",
      "시도 시군구 뷰 만들기",
      "시도 시군구 저장프로시저 만들기",
      "Company 뷰, 저장함수 만들기",
      "테스트화면 개발, Model 클래스 개발",
      "사용자(직원) 만들기",
      "User 완성하기",
      "1:1관계를 가지고 사용자 속성 확장",
      "bit (boolean) 타입의 함정",
      "회사, 사용자 조회 및 삭제 구현",
      "삭제 트랜잭션 구현하기"
    ]
  },
  {
    "title": "Advanced Course",
    "image": "3.png",
    "content": "전문가 과정으로 Basic Course, Intermediate course를 이수한 회원으로 전문 프로그램 과정",
    "time": "180시간 12주 교육",
    "tags": ["해부학", "생리학"],
    "star": 5,
    "instructor": "강사명",
    "subtitle": "🔥 데이터베이스 설계 기초편에 이은 두 번째 강의입니다.",
    "keywords": ["데이터베이스 모델링 실전", "데이터베이스 설계"],
    "description": "실전 프로젝트를 대상으로 처음부터 끝까지 만들어보는 실전 위주의 수업이며, 강의 내용을 모두 이해하고 나면 자유자재로 데이터베이스 설계를 하실 수 있는 능력을 갖출 수 있습니다.",
    "banner": "그 누구도 알려주지 않았던 SQL, 잘 작성하고, 해석하고, 검증하는 비법 레시피!",
    "curriculum": [
      "사용자(회사), 시도, 시군구 테이블 만들기",
      "시도 시군구 뷰 만들기",
      "시도 시군구 저장프로시저 만들기",
      "Company 뷰, 저장함수 만들기",
      "테스트화면 개발, Model 클래스 개발",
      "사용자(직원) 만들기",
      "User 완성하기",
      "1:1관계를 가지고 사용자 속성 확장",
      "bit (boolean) 타입의 함정",
      "회사, 사용자 조회 및 삭제 구현",
      "삭제 트랜잭션 구현하기"
    ]
  }
]
